ppmm/__init__.py
ppmm/cli.py
ppmm/core.py
ppmm/data.json
ppmm-1.2.2.dist-info/METADATA
ppmm-1.2.2.dist-info/WHEEL
ppmm-1.2.2.dist-info/entry_points.txt
ppmm-1.2.2.dist-info/licenses/LICENSE
ppmm-1.2.2.dist-info/RECORD
