Metadata-Version: 2.4
Name: ppmm
Version: 1.2.2
Summary: 一个简单的pip镜像管理工具
Project-URL: repository, https://github.com/LanMist/ppmm
Author-email: XuLan <xuzn@msn.com>
License: MIT
License-File: LICENSE
Requires-Python: >=3.6
